<?xml version="1.0" encoding="UTF-8" ?>
<!DOCTYPE mapper PUBLIC "-//mybatis.org//DTD Mapper 3.0//EN" "http://mybatis.org/dtd/mybatis-3-mapper.dtd" >
<mapper namespace="com.example.kafka_test.dao.LineVideoConfigDao" >
  <resultMap id="BaseResultMap" type="com.example.kafka_test.pojo.LineVideoConfig" >
    <!--
      WARNING - @mbggenerated
      This element is automatically generated by MyBatis Generator, do not modify.
    -->
    <id column="id" property="id" jdbcType="INTEGER" />
    <result column="line_classify_level1_id" property="lineClassifyLevel1Id" jdbcType="INTEGER" />
    <result column="line_classify_level2_id" property="lineClassifyLevel2Id" jdbcType="INTEGER" />
    <result column="line_classify_level3_id" property="lineClassifyLevel3Id" jdbcType="INTEGER" />
    <result column="line_classify_level4_id" property="lineClassifyLevel4Id" jdbcType="INTEGER" />
    <result column="video_url" property="videoUrl" jdbcType="VARCHAR" />
    <result column="place" property="place" jdbcType="VARCHAR" />
    <result column="del" property="del" jdbcType="BIT" />
    <result column="create_time" property="createTime" jdbcType="TIMESTAMP" />
    <result column="update_time" property="updateTime" jdbcType="TIMESTAMP" />
    <result column="create_source" property="createSource" jdbcType="VARCHAR" />
    <result column="update_source" property="updateSource" jdbcType="VARCHAR" />
  </resultMap>
  <sql id="Base_Column_List" >
    <!--
      WARNING - @mbggenerated
      This element is automatically generated by MyBatis Generator, do not modify.
    -->
    id, line_classify_level1_id, line_classify_level2_id, line_classify_level3_id, line_classify_level4_id, 
    video_url, place, del, create_time, update_time, create_source, update_source
  </sql>
  <select id="selectByPrimaryKey" resultMap="BaseResultMap" parameterType="java.lang.Integer" >
    <!--
      WARNING - @mbggenerated
      This element is automatically generated by MyBatis Generator, do not modify.
    -->
    select 
    <include refid="Base_Column_List" />
    from line_video_config
    where id = #{id,jdbcType=INTEGER}
  </select>
  <delete id="deleteByPrimaryKey" parameterType="java.lang.Integer" >
    <!--
      WARNING - @mbggenerated
      This element is automatically generated by MyBatis Generator, do not modify.
    -->
    delete from line_video_config
    where id = #{id,jdbcType=INTEGER}
  </delete>
  <insert id="insert" parameterType="com.example.kafka_test.pojo.LineVideoConfig" useGeneratedKeys="true" keyProperty="id" >
    <!--
      WARNING - @mbggenerated
      This element is automatically generated by MyBatis Generator, do not modify.
    -->
    insert into line_video_config ( line_classify_level1_id, line_classify_level2_id,
      line_classify_level3_id, line_classify_level4_id, 
      video_url, place,  create_source, update_source
      )
    values ( #{lineClassifyLevel1Id,jdbcType=INTEGER}, #{lineClassifyLevel2Id,jdbcType=INTEGER},
      #{lineClassifyLevel3Id,jdbcType=INTEGER}, #{lineClassifyLevel4Id,jdbcType=INTEGER}, 
      #{videoUrl,jdbcType=VARCHAR}, #{place,jdbcType=VARCHAR}, #{createSource,jdbcType=VARCHAR}, #{updateSource,jdbcType=VARCHAR}
      )
  </insert>
  <insert id="insertSelective" parameterType="com.example.kafka_test.pojo.LineVideoConfig" useGeneratedKeys="true" keyProperty="id">
    <!--
      WARNING - @mbggenerated
      This element is automatically generated by MyBatis Generator, do not modify.
    -->
    insert into line_video_config
    <trim prefix="(" suffix=")" suffixOverrides="," >
      <if test="id != null" >
        id,
      </if>
      <if test="lineClassifyLevel1Id != null" >
        line_classify_level1_id,
      </if>
      <if test="lineClassifyLevel2Id != null" >
        line_classify_level2_id,
      </if>
      <if test="lineClassifyLevel3Id != null" >
        line_classify_level3_id,
      </if>
      <if test="lineClassifyLevel4Id != null" >
        line_classify_level4_id,
      </if>
      <if test="videoUrl != null" >
        video_url,
      </if>
      <if test="place != null" >
        place,
      </if>
      <if test="del != null" >
        del,
      </if>
      <if test="createTime != null" >
        create_time,
      </if>
      <if test="updateTime != null" >
        update_time,
      </if>
      <if test="createSource != null" >
        create_source,
      </if>
      <if test="updateSource != null" >
        update_source,
      </if>
    </trim>
    <trim prefix="values (" suffix=")" suffixOverrides="," >
      <if test="id != null" >
        #{id,jdbcType=INTEGER},
      </if>
      <if test="lineClassifyLevel1Id != null" >
        #{lineClassifyLevel1Id,jdbcType=INTEGER},
      </if>
      <if test="lineClassifyLevel2Id != null" >
        #{lineClassifyLevel2Id,jdbcType=INTEGER},
      </if>
      <if test="lineClassifyLevel3Id != null" >
        #{lineClassifyLevel3Id,jdbcType=INTEGER},
      </if>
      <if test="lineClassifyLevel4Id != null" >
        #{lineClassifyLevel4Id,jdbcType=INTEGER},
      </if>
      <if test="videoUrl != null" >
        #{videoUrl,jdbcType=VARCHAR},
      </if>
      <if test="place != null" >
        #{place,jdbcType=VARCHAR},
      </if>
      <if test="del != null" >
        #{del,jdbcType=BIT},
      </if>
      <if test="createTime != null" >
        #{createTime,jdbcType=TIMESTAMP},
      </if>
      <if test="updateTime != null" >
        #{updateTime,jdbcType=TIMESTAMP},
      </if>
      <if test="createSource != null" >
        #{createSource,jdbcType=VARCHAR},
      </if>
      <if test="updateSource != null" >
        #{updateSource,jdbcType=VARCHAR},
      </if>
    </trim>
  </insert>
  <update id="updateByPrimaryKeySelective" parameterType="com.example.kafka_test.pojo.LineVideoConfig" >
    <!--
      WARNING - @mbggenerated
      This element is automatically generated by MyBatis Generator, do not modify.
    -->
    update line_video_config
    <set >
      <if test="lineClassifyLevel1Id != null" >
        line_classify_level1_id = #{lineClassifyLevel1Id,jdbcType=INTEGER},
      </if>
      <if test="lineClassifyLevel2Id != null" >
        line_classify_level2_id = #{lineClassifyLevel2Id,jdbcType=INTEGER},
      </if>
      <if test="lineClassifyLevel3Id != null" >
        line_classify_level3_id = #{lineClassifyLevel3Id,jdbcType=INTEGER},
      </if>
      <if test="lineClassifyLevel4Id != null" >
        line_classify_level4_id = #{lineClassifyLevel4Id,jdbcType=INTEGER},
      </if>
      <if test="videoUrl != null" >
        video_url = #{videoUrl,jdbcType=VARCHAR},
      </if>
      <if test="place != null" >
        place = #{place,jdbcType=VARCHAR},
      </if>
      <if test="del != null" >
        del = #{del,jdbcType=BIT},
      </if>
      <if test="createTime != null" >
        create_time = #{createTime,jdbcType=TIMESTAMP},
      </if>
      <if test="updateTime != null" >
        update_time = #{updateTime,jdbcType=TIMESTAMP},
      </if>
      <if test="createSource != null" >
        create_source = #{createSource,jdbcType=VARCHAR},
      </if>
      <if test="updateSource != null" >
        update_source = #{updateSource,jdbcType=VARCHAR},
      </if>
    </set>
    where id = #{id,jdbcType=INTEGER}
  </update>
  <update id="updateByPrimaryKey" parameterType="com.example.kafka_test.pojo.LineVideoConfig" >
    <!--
      WARNING - @mbggenerated
      This element is automatically generated by MyBatis Generator, do not modify.
    -->
    update line_video_config
    set line_classify_level1_id = #{lineClassifyLevel1Id,jdbcType=INTEGER},
      line_classify_level2_id = #{lineClassifyLevel2Id,jdbcType=INTEGER},
      line_classify_level3_id = #{lineClassifyLevel3Id,jdbcType=INTEGER},
      line_classify_level4_id = #{lineClassifyLevel4Id,jdbcType=INTEGER},
      video_url = #{videoUrl,jdbcType=VARCHAR},
      place = #{place,jdbcType=VARCHAR},
      del = #{del,jdbcType=BIT},
      create_time = #{createTime,jdbcType=TIMESTAMP},
      update_time = #{updateTime,jdbcType=TIMESTAMP},
      create_source = #{createSource,jdbcType=VARCHAR},
      update_source = #{updateSource,jdbcType=VARCHAR}
    where id = #{id,jdbcType=INTEGER}
  </update>
</mapper>